epp_logs_to_sqlite/__init__.py
epp_logs_to_sqlite/__main__.py
epp_logs_to_sqlite/db_writer.py
epp_logs_to_sqlite/event_log_entry_extra_data.py
epp_logs_to_sqlite/logs_to_db.py
epp_logs_to_sqlite/util.py
epp_logs_to_sqlite-2.0.dist-info/LICENSE
epp_logs_to_sqlite-2.0.dist-info/METADATA
epp_logs_to_sqlite-2.0.dist-info/WHEEL
epp_logs_to_sqlite-2.0.dist-info/top_level.txt
epp_logs_to_sqlite-2.0.dist-info/RECORD
